README.md
setup.py
urbandictionary_top.py
urbandictionary_top.egg-info/PKG-INFO
urbandictionary_top.egg-info/SOURCES.txt
urbandictionary_top.egg-info/dependency_links.txt
urbandictionary_top.egg-info/requires.txt
urbandictionary_top.egg-info/top_level.txt