Metadata-Version: 1.1
Name: urbandictionary-top
Version: 0.3
Summary: A dead simple module that fetches the top definition and example of a term from urbandictionary. (https://urbandictionary.com)
Home-page: https://github.com/laymonage/urbandictionary_top-python
Author: sage
Author-email: laymonage@gmail.com
License: UNKNOWN
Download-URL: https://github.com/laymonage/urbandictionary_top-python/archive/0.3.tar.gz
Keywords: urban,dictionary,urbandictionary,top,definition,example
Platform: UNKNOWN
